tools4sci/__init__.py
tools4sci/formulas.py
tools4sci/io.py
tools4sci/report.py
tools4sci/simulate.py
tools4sci/stats.py
tools4sci-0.0.1.4.dist-info/METADATA
tools4sci-0.0.1.4.dist-info/WHEEL
tools4sci-0.0.1.4.dist-info/licenses/LICENSE
tools4sci-0.0.1.4.dist-info/RECORD
