Metadata-Version: 2.4
Name: tools4sci
Version: 0.0.1.4
Summary: Utility functions for quantitative analysis in science.
Project-URL: Homepage, https://github.com/DiogoFerrari/tools4sci
Project-URL: Documentation, https://github.com/DiogoFerrari/tools4sci
Project-URL: Changelog, https://github.com/DiogoFerrari/tools4sci/blob/master/CHANGELOG.md
Project-URL: Issues, https://github.com/DiogoFerrari/tools4sci/issues/
Author-email: Diogo Ferrari <diogoferrari@gmail.com>
Maintainer-email: Diogo Ferrari <diogoferrari@gmail.com>
License-Expression: MIT
License-File: LICENSE
Keywords: Data analysis,Research,Utilities
Classifier: Development Status :: 4 - Beta
Classifier: Intended Audience :: Science/Research
Classifier: Topic :: Scientific/Engineering
Requires-Python: >=3.6
Requires-Dist: altair
Requires-Dist: ghostscript
Requires-Dist: pandas
Requires-Dist: plotnine
Requires-Dist: polars
Requires-Dist: tidypolars4sci
Requires-Dist: typing
Requires-Dist: vl-convert-python
Requires-Dist: xlsxwriter
